LICENSE
MANIFEST.in
setup.py
effipy/__init__.py
effipy/contracts.py
effipy/customers.py
effipy/efficiencyreports.py
effipy/invoice_measures.py
effipy/invoices.py
effipy/measures.py
effipy/meters.py
effipy/readings.py
effipy/resource.py
effipy/service.py
effipy/tariffs.py
effipy/test_server.py
effipy/usagepoints.py
effipy.egg-info/PKG-INFO
effipy.egg-info/SOURCES.txt
effipy.egg-info/dependency_links.txt
effipy.egg-info/not-zip-safe
effipy.egg-info/requires.txt
effipy.egg-info/top_level.txt