Metadata-Version: 1.0
Name: effipy
Version: 0.6.1
Summary: Python library for the Effipeople REST API.
Home-page: http://code.gisce.net/effipy
Author: GISCE-TI, S.L.
Author-email: devel@gisce.net
License: MIT
Platform: UNKNOWN
Classifier: Intended Audience :: Developers
Classifier: Operating System :: OS Independent
Classifier: Programming Language :: Python
Classifier: Topic :: Software Development :: Libraries :: Python Modules
